sample_testcoder/__init__.py
sample_testcoder/hello.py
sample_testcoder/hellot.py
sample_testcoder/calculations/__init__.py
sample_testcoder/calculations/add.py
sample_testcoder/calculations/subtract.py
sample_testcoder-0.0.4.dist-info/METADATA
sample_testcoder-0.0.4.dist-info/WHEEL
sample_testcoder-0.0.4.dist-info/top_level.txt
sample_testcoder-0.0.4.dist-info/RECORD
