Metadata-Version: 2.1
Name: sample-testcoder
Version: 0.0.4
Summary: My very first Python package
Home-page: UNKNOWN
Author: Test Last
Author-email: <testlast@email.com>
License: UNKNOWN
Keywords: python,first package
Platform: UNKNOWN
Classifier: Development Status :: 3 - Alpha
Classifier: Intended Audience :: Education
Classifier: Programming Language :: Python :: 2
Classifier: Programming Language :: Python :: 3
Classifier: Operating System :: MacOS :: MacOS X
Classifier: Operating System :: Microsoft :: Windows
Requires-Python: >=3
Requires-Dist: bpython
Requires-Dist: numpy
